FIR/Verilog Files/FIR.v
module FIR_Hamming_Lowpass_ (Data_out, Data_in, clock, reset);
	parameter order = 8;
	parameter word_size_in = 8;
	parameter word_size_out = 2*word_size_in+2;
	
	parameter b0=8'd11;
	parameter b1=8'd7;
	parameter b2=8'd0;
	parameter b3=8'd61;
	parameter b4=8'd127;
	parameter b5=8'd61;
	parameter b6=8'd0;
	parameter b7=8'd7;
	parameter b8=8'd11;

	output[word_size_out-1:0] Data_out;
	input[word_size_in-1:0] Data_in;
	input clock, reset;
	reg [word_size_in-1:0] Samples[1:order];
	
	integer k;
	
	assign Data_out=b0*Data_in+b1*Samples[1]+b2*Samples[2]+b3*Samples[3]+b4*Samples[4]+b5*Samples[5]+b6*Samples[6]+b7*Samples[7]+b8*Samples[8];
	
	always @ (posedge clock)
		if (reset==1) begin for (k=1;k<=order;k=k+1) Samples [k]=0; end
		else begin
			Samples[1]<=Data_in;
			for (k=2;k<=order;k=k+1) Samples[k]<=Samples[k-1];
		end
endmodule

FIR/Verilog Files/FIR_testbench.v
`timescale 1ns/10ps
module FIR_testbench;
	parameter word_size_in = 8;
	parameter word_size_out = 2*word_size_in+2;

	reg[word_size_in-1:0] Data_in;
	reg clock, reset;
	wire[word_size_out-1:0] Data_out;

	FIR_Hamming_Lowpass_ DUT (
		.clock(clock),
		.reset(reset), 
		.Data_in(Data_in),
		.Data_out(Data_out)
	);

    	initial 
        begin
           clock = 1'b0;
	   forever 
	   begin
	      #10416 clock = ~clock;
	      $display("At Time: %d  Filter Output=%d",$time,Data_out);
	   end  
        end

	initial
	begin
	  #0  reset=1;
	  Data_in=8'd0;
	  #20832  reset=0;
	  #20833  Data_in=8'd52;
	  #20834  Data_in=8'd198;
	  #20833  Data_in=8'd96;
	  #20833  Data_in=8'd36;
	  #20834  Data_in=8'd17;
	  #20833  Data_in=8'd226;
	  #20833  Data_in=8'd210;
	  #20834  Data_in=8'd153;
	  #20833  Data_in=8'd150;
	  #20833  Data_in=8'd143;
	  #20834  Data_in=8'd143;
	  #20833  Data_in=8'd220;
	  #20833  Data_in=8'd235;
	  #20834  Data_in=8'd23;
	  #20833  Data_in=8'd19;
	  #20833  Data_in=8'd108;
	  #20834  Data_in=8'd202;
	  #20833  Data_in=8'd62;
	  #20833  Data_in=8'd21;
	  #20834  Data_in=8'd42;
	  #20833  Data_in=8'd192;
	  #20833  Data_in=8'd83;
	  #20834  Data_in=8'd53;
	  #20833  Data_in=8'd13;
	  #20833  Data_in=8'd216;
	  #20834  Data_in=8'd200;
	  #20833  Data_in=8'd163;
	  #20833  Data_in=8'd155;
	  #20834  Data_in=8'd136;
	  #20833  Data_in=8'd132;
	  #20833  Data_in=8'd229;
	  #20834  Data_in=8'd242;
	  #20833  Data_in=8'd30;
	  #20833  Data_in=8'd2;
	  #20834  Data_in=8'd119;
	  #20833  Data_in=8'd205;
	  #20833  Data_in=8'd73;
	  #20834  Data_in=8'd42;
	  #20833  Data_in=8'd34;
	  #20833  Data_in=8'd185;
	  #20834  Data_in=8'd69;
	  #20833  Data_in=8'd69;
	  #20833  Data_in=8'd9;
	  #20834  Data_in=8'd204;
	  #20833  Data_in=8'd188;
	  #20833  Data_in=8'd172;
	  #20834  Data_in=8'd158;
	  #20833  Data_in=8'd127;
	  #20833  Data_in=8'd121;
	  #20834  Data_in=8'd237;
	  #20833  Data_in=8'd248;
	  #20833  Data_in=8'd38;
	  #20834  Data_in=8'd13;
	  #20833  Data_in=8'd129;
	  #20833  Data_in=8'd206;
	  #20834  Data_in=8'd85;
	  #20833  Data_in=8'd63;
	  #20833  Data_in=8'd26;
	  #20834  Data_in=8'd177;
	  #20833  Data_in=8'd55;
	  #20833  Data_in=8'd85;
	  #20834  Data_in=8'd7;
	  #20833  Data_in=8'd190;
	  #20833  Data_in=8'd176;
	  #20834  Data_in=8'd180;
	  #20833  Data_in=8'd160;
	  #20833  Data_in=8'd116;
	  #20834  Data_in=8'd110;
	  #20833  Data_in=8'd243;
	  #20833  Data_in=8'd252;
	  #20834  Data_in=8'd46;
	  #20833  Data_in=8'd30;
	  #20833  Data_in=8'd138;
	  #20834  Data_in=8'd206;
	  #20833  Data_in=8'd97;
	  #20833  Data_in=8'd83;
	  #20834  Data_in=8'd20;
	  #20833  Data_in=8'd167;
	  #20833  Data_in=8'd40;
	  #20834  Data_in=8'd100;
	  #20833  Data_in=8'd6;
	  #20833  Data_in=8'd176;
	  #20834  Data_in=8'd164;
	  #20833  Data_in=8'd187;
	  #20833  Data_in=8'd160;
	  #20834  Data_in=8'd104;
	  #20833  Data_in=8'd99;
	  #20833  Data_in=8'd248;
	  #20834  Data_in=8'd255;
	  #20833  Data_in=8'd55;
	  #20833  Data_in=8'd46;
	  #20834  Data_in=8'd145;
	  #20833  Data_in=8'd205;
	  #20833  Data_in=8'd110;
	  #20834  Data_in=8'd103;
	  #20833  Data_in=8'd14;
	  #20833  Data_in=8'd156;
	  #20834  Data_in=8'd24;
	  #20833  Data_in=8'd115;
	  #20833  Data_in=8'd6;
	  #20834  Data_in=8'd160;
	  #20833  Data_in=8'd151;
	  #20833  Data_in=8'd193;
	  #20834  Data_in=8'd159;
	  #20833  Data_in=8'd92;
	  #20833  Data_in=8'd88;
	  #20834  Data_in=8'd252;
	  #20833  Data_in=8'd255;
	  #20833  Data_in=8'd65;
	  #20834  Data_in=8'd61;
	  #20833  Data_in=8'd151;
	  #20833  Data_in=8'd203;
	  #20834  Data_in=8'd123;
	  #20833  Data_in=8'd122;
	  #20833  Data_in=8'd10;
	  #20834  Data_in=8'd144;
	  #20833  Data_in=8'd9;
	  #20833  Data_in=8'd129;
	  #20834  Data_in=8'd7;
	  #20832  $stop;
	end

	initial 
	begin
		$dumpfile("FIR_dump.vcd");
		$dumpvars;
	end
endmodule

FIR/Modelsim Files/FIR_dump.vcd
$date
	Mon Apr 12 21:04:48 2021
$end
$version
	ModelSim Version 10.5b
$end
$timescale
	10ps
$end

$scope module FIR_testbench $end
$var parameter 32 ! word_size_in $end
$var parameter 32 " word_size_out $end
$var reg 8 # Data_in [7:0] $end
$var reg 1 $ clock $end
$var reg 1 % reset $end
$var wire 1 & Data_out [17] $end
$var wire 1 ' Data_out [16] $end
$var wire 1 ( Data_out [15] $end
$var wire 1 ) Data_out [14] $end
$var wire 1 * Data_out [13] $end
$var wire 1 + Data_out [12] $end
$var wire 1 , Data_out [11] $end
$var wire 1 - Data_out [10] $end
$var wire 1 . Data_out [9] $end
$var wire 1 / Data_out [8] $end
$var wire 1 0 Data_out [7] $end
$var wire 1 1 Data_out [6] $end
$var wire 1 2 Data_out [5] $end
$var wire 1 3 Data_out [4] $end
$var wire 1 4 Data_out [3] $end
$var wire 1 5 Data_out [2] $end
$var wire 1 6 Data_out [1] $end
$var wire 1 7 Data_out [0] $end

$scope module DUT $end
$var parameter 32 8 order $end
$var parameter 32 9 word_size_in $end
$var parameter 32 : word_size_out $end
$var parameter 8 ; b0 $end
$var parameter 8 < b1 $end
$var parameter 8 = b2 $end
$var parameter 8 > b3 $end
$var parameter 8 ? b4 $end
$var parameter 8 @ b5 $end
$var parameter 8 A b6 $end
$var parameter 8 B b7 $end
$var parameter 8 C b8 $end
$var wire 1 & Data_out [17] $end
$var wire 1 ' Data_out [16] $end
$var wire 1 ( Data_out [15] $end
$var wire 1 ) Data_out [14] $end
$var wire 1 * Data_out [13] $end
$var wire 1 + Data_out [12] $end
$var wire 1 , Data_out [11] $end
$var wire 1 - Data_out [10] $end
$var wire 1 . Data_out [9] $end
$var wire 1 / Data_out [8] $end
$var wire 1 0 Data_out [7] $end
$var wire 1 1 Data_out [6] $end
$var wire 1 2 Data_out [5] $end
$var wire 1 3 Data_out [4] $end
$var wire 1 4 Data_out [3] $end
$var wire 1 5 Data_out [2] $end
$var wire 1 6 Data_out [1] $end
$var wire 1 7 Data_out [0] $end
$var wire 1 D Data_in [7] $end
$var wire 1 E Data_in [6] $end
$var wire 1 F Data_in [5] $end
$var wire 1 G Data_in [4] $end
$var wire 1 H Data_in [3] $end
$var wire 1 I Data_in [2] $end
$var wire 1 J Data_in [1] $end
$var wire 1 K Data_in [0] $end
$var wire 1 L clock $end
$var wire 1 M reset $end
$var integer 32 N k $end
$upscope $end
$upscope $end
$enddefinitions $end
#0
$dumpvars
b0 #
0$
1%
b1000 !
b10010 "
b1000 8
b1000 9
b10010 :
b1011 ;
b111 <
b0 =
b111101 >
b1111111 ?
b111101 @
b0 A
b111 B
b1011 C
bx N
x7
x6
x5
x4
x3
x2
x1
x0
x/
x.
x-
x,
x+
x*
x)
x(
x'
x&
0K
0J
0I
0H
0G
0F
0E
0D
1M
0L
$end
#1041600
1$
1L
b1 N
b10 N
b11 N
b100 N
b101 N
b110 N
b111 N
b1000 N
b1001 N
07
06
05
04
03
02
01
00
0/
0.
0-
0,
0+
0*
0)
0(
0'
0&
#2083200
0%
0$
0M
0L
#3124800
1$
1L
b10 N
b11 N
b100 N
b101 N
b110 N
b111 N
b1000 N
b1001 N
#4166400
0$
0L
#4166500
b110100 #
1I
1G
1F
15
14
13
12
1.
#5208000
1$
1L
b10 N
b11 N
b100 N
b101 N
b110 N
b111 N
b1000 N
b1001 N
05
03
10
1/
#6249600
0$
0L
#6249900
b11000110 #
1J
0G
0F
1E
1D
16
15
11
0.
1,
#7291200
1$
1L
b10 N
b11 N
b100 N
b101 N
b110 N
b111 N
b1000 N
b1001 N
06
1-
#8332800
0$
0L
#8333200
b1100000 #
0J
0I
1F
0D
16
05
02
01
0-
#9374400
1$
1L
b10 N
b11 N
b100 N
b101 N
b110 N
b111 N
b1000 N
b1001 N
06
15
04
12
00
1.
0,
1+
#10416000
0$
0L
#10416500
b100100 #
1I
0E
05
13
02
10
0/
0.
#11457600
1$
1L
b10 N
b11 N
b100 N
b101 N
b110 N
b111 N
b1000 N
b1001 N
16
03
1/
1.
1,
0+
1)
#12499200
0$
0L
#12499900
b10001 #
1K
0I
1G
0F
17
06
13
12
0/
#13540800
1$
1L
b10 N
b11 N
b100 N
b101 N
b110 N
b111 N
b1000 N
b1001 N
07
1-
0,
0)
1(
#14582400
0$
0L
#14583200
b11100010 #
0K
1J
0G
1F
1E
1D
17
16
14
03
1/
1,
#15624000
1$
1L
b10 N
b11 N
b100 N
b101 N
b110 N
b111 N
b1000 N
b1001 N
07
15
04
02
11
00
0,
1+
1*
1)
0(
#16665600
0$
0L
#16666500
b11010010 #
1G
0F
13
01
10
0/
#17707200
1$
1L
b10 N
b11 N
b100 N
b101 N
b110 N
b111 N
b1000 N
b1001 N
17
06
05
14
12
11
0.
1,
0)
#18748800
0$
0L
#18749900
b10011001 #
1K
0J
1H
0E
07
16
15
04
03
02
01
1.
0-
#19790400
1$
1L
b10 N
b11 N
b100 N
b101 N
b110 N
b111 N
b1000 N
b1001 N
17
06
11
00
1/
0.
0*
1)
#20832000
0$
0L
#20833200
b10010110 #
0K
1J
1I
0H
07
12
01
#21873600
1$
1L
b10 N
b11 N
b100 N
b101 N
b110 N
b111 N
b1000 N
b1001 N
17
16
05
11
10
1.
1*
0)
1(
#22915200
0$
0L
#22916500
b10001111 #
1K
1H
0G
07
15
13
02
01
#23956800
1$
1L
b10 N
b11 N
b100 N
b101 N
b110 N
b111 N
b1000 N
b1001 N
17
03
12
0.
0,
0*
1)
#24998400
0$
0L
#26040000
1$
1L
b10 N
b11 N
b100 N
b101 N
b110 N
b111 N
b1000 N
b1001 N
07
06
05
02
11
1-
1,
0+
1*
0)
#27081600
0$
0L
#27083200
b11011100 #
0K
0J
1G
1E
17
16
15
14
01
00
0-
0,
1+
#28123200
1$
1L
b10 N
b11 N
b100 N
b101 N
b110 N
b111 N
b1000 N
b1001 N
05
04
13
11
1.
1-
0+
#29164800
0$
0L
#29166500
b11101011 #
1K
1J
0I
0G
1F
07
06
14
12
10
#30206400
1$
1L
b10 N
b11 N
b100 N
b101 N
b110 N
b111 N
b1000 N
b1001 N
15
01
0/
0.
1,
#31248000
0$
0L
#31249900
b10111 #
1I
0H
1G
0F
0E
0D
05
04
03
1/
1.
0-
0,
#32289600
1$
1L
b10 N
b11 N
b100 N
b101 N
b110 N
b111 N
b1000 N
b1001 N
17
16
02
11
00
0/
0.
1-
1,
#33331200
0$
0L
#33333200
b10011 #
0I
15
13
01
#34372800
1$
1L
b10 N
b11 N
b100 N
b101 N
b110 N
b111 N
b1000 N
b1001 N
06
05
14
12
1/
1.
0-
0,
1+
0*
1)
#35414400
0$
0L
#35416500
b1101100 #
0K
0J
1I
1H
0G
1F
1E
07
15
03
02
1-
#36456000
1$
1L
b10 N
b11 N
b100 N
b101 N
b110 N
b111 N
b1000 N
b1001 N
17
16
12
11
0/
0.
0-
0+
#37497600
0$
0L
#37499900
b11001010 #
1J
0I
0F
1D
06
05
13
1-
#38539200
1$
1L
b10 N
b11 N
b100 N
b101 N
b110 N
b111 N
b1000 N
b1001 N
04
01
0-
1*
0(
#39580800
0$
0L
#39583200
b111110 #
1I
1G
1F
0E
0D
15
14
03
1.
1,
1+
0*
#40622400
1$
1L
b10 N
b11 N
b100 N
b101 N
b110 N
b111 N
b1000 N
b1001 N
05
1/
0.
1*
0)
#41664000
0$
0L
#41666500
b10101 #
1K
0J
0H
0F
07
16
15
04
11
1.
1-
0,
#42705600
1$
1L
b10 N
b11 N
b100 N
b101 N
b110 N
b111 N
b1000 N
b1001 N
06
05
14
13
02
01
10
0-
1,
1)
#43747200
0$
0L
#43749900
b101010 #
0K
1J
0I
1H
0G
1F
17
16
15
12
11
00
0/
0.
1-
#44788800
1$
1L
b10 N
b11 N
b100 N
b101 N
b110 N
b111 N
b1000 N
b1001 N
07
04
03
1.
0-
0*
0)
1(
#45830400
0$
0L
#45833200
b11000000 #
0J
0H
0F
1E
1D
06
05
14
13
02
10
0.
0,
0+
1*
#46872000
1$
1L
b10 N
b11 N
b100 N
b101 N
b110 N
b111 N
b1000 N
b1001 N
17
16
15
04
03
12
1.
1)
0(
#47913600
0$
0L
#47916500
b1010011 #
1K
1J
1G
0D
07
06
05
14
13
01
00
1-
1,
1+
0*
#48955200
1$
1L
b10 N
b11 N
b100 N
b101 N
b110 N
b111 N
b1000 N
b1001 N
16
15
03
02
11
10
0.
0+
1*
0)
#49996800
0$
0L
#49999900
b110101 #
0J
1I
1F
0E
06
04
01
1/
1.
0-
#51038400
1$
1L
b10 N
b11 N
b100 N
b101 N
b110 N
b111 N
b1000 N
b1001 N
17
16
05
14
13
12
11
00
0.
1-
0,
1+
0*
1)
#52080000
0$
0L
#52083200
b1101 #
1H
0G
0F
04
03
02
10
1.
0-
#53121600
1$
1L
b10 N
b11 N
b100 N
b101 N
b110 N
b111 N
b1000 N
b1001 N
13
00
0/
0.
1,
0+
0)
1(
#54163200
0$
0L
#54166500
b11011000 #
0K
0I
1G
1E
1D
07
06
15
14
03
01
1/
0,
1+
#55204800
1$
1L
b10 N
b11 N
b100 N
b101 N
b110 N
b111 N
b1000 N
b1001 N
17
16
05
13
12
11
10
1-
1*
1)
0(
#56246400
0$
0L
#56249900
b11001000 #
0G
03
02
00
#57288000
1$
1L
b10 N
b11 N
b100 N
b101 N
b110 N
b111 N
b1000 N
b1001 N
07
06
0-
0+
0*
#58329600
0$
0L
#58333200
b10100011 #
1K
1J
0H
1F
0E
17
04
13
12
01
10
1.
1-
1,
1+
1*
0)
#59371200
1$
1L
b10 N
b11 N
b100 N
b101 N
b110 N
b111 N
b1000 N
b1001 N
07
02
00
0.
0-
0*
1)
#60412800
0$
0L
#60416500
b10011011 #
1H
1G
0F
14
12
10
0/
#61454400
1$
1L
b10 N
b11 N
b100 N
b101 N
b110 N
b111 N
b1000 N
b1001 N
15
04
02
11
00
1/
1.
0,
1*
0)
1(
#62496000
0$
0L
#62499900
b10001000 #
0K
0J
0G
17
16
05
03
01
10
0/
#63537600
1$
1L
b10 N
b11 N
b100 N
b101 N
b110 N
b111 N
b1000 N
b1001 N
14
13
00
0.
1-
1,
0+
0*
1)
#64579200
0$
0L
#64583200
b10000100 #
1I
0H
15
03
12
11
10
1/
1.
0-
#65620800
1$
1L
b10 N
b11 N
b100 N
b101 N
b110 N
b111 N
b1000 N
b1001 N
07
13
02
00
0.
0,
1+
1*
0)
#66662400
0$
0L
#66666500
b11100101 #
1K
1F
1E
17
06
05
03
01
10
1-
#67704000
1$
1L
b10 N
b11 N
b100 N
b101 N
b110 N
b111 N
b1000 N
b1001 N
15
04
13
12
0/
1.
0-
1,
0+
#68745600
0$
0L
#68749900
b11110010 #
0K
1J
0I
1G
07
03
02
11
00
1/
#69787200
1$
1L
b10 N
b11 N
b100 N
b101 N
b110 N
b111 N
b1000 N
b1001 N
17
16
14
13
01
10
1-
0,
#70828800
0$
0L
#70833200
b11110 #
1I
1H
0F
0E
0D
05
04
03
0/
1,
1+
0*
#71870400
1$
1L
b10 N
b11 N
b100 N
b101 N
b110 N
b111 N
b1000 N
b1001 N
07
15
14
13
1/
0,
0+
1*
#72912000
0$
0L
#72916500
b10 #
0I
0H
0G
05
03
12
11
00
0/
#73953600
1$
1L
b10 N
b11 N
b100 N
b101 N
b110 N
b111 N
b1000 N
b1001 N
17
13
02
01
1+
0*
1)
#74995200
0$
0L
#74999900
b1110111 #
1K
1I
1G
1F
1E
07
04
03
12
1/
0-
1,
#76036800
1$
1L
b10 N
b11 N
b100 N
b101 N
b110 N
b111 N
b1000 N
b1001 N
06
15
02
10
0/
0.
0+
#77078400
0$
0L
#77083200
b11001101 #
0J
1H
0G
0F
1D
16
13
12
00
1-
#78120000
1$
1L
b10 N
b11 N
b100 N
b101 N
b110 N
b111 N
b1000 N
b1001 N
06
03
11
10
0-
0,
1*
0(
#79161600
0$
0L
#79166500
b1001001 #
0I
0D
05
14
13
01
00
1/
1.
1,
1+
0*
#80203200
1$
1L
b10 N
b11 N
b100 N
b101 N
b110 N
b111 N
b1000 N
b1001 N
04
02
10
0.
1-
0,
1*
0)
#81244800
0$
0L
#81249900
b101010 #
0K
1J
1F
0E
17
16
14
12
00
0/
#82286400
1$
1L
b10 N
b11 N
b100 N
b101 N
b110 N
b111 N
b1000 N
b1001 N
06
15
04
03
02
11
10
1/
1.
1,
1)
#83328000
0$
0L
#83333200
b100010 #
0H
14
12
00
#84369600
1$
1L
b10 N
b11 N
b100 N
b101 N
b110 N
b111 N
b1000 N
b1001 N
16
02
01
0.
0-
0,
0+
0)
1(
#85411200
0$
0L
#85416500
b10111001 #
1K
0J
1H
1G
1D
07
06
10
1.
1-
#86452800
1$
1L
b10 N
b11 N
b100 N
b101 N
b110 N
b111 N
b1000 N
b1001 N
12
11
00
0.
1,
1)
0(
#87494400
0$
0L
#87499900
b1000101 #
1I
0H
0G
0F
1E
0D
05
04
13
0/
0-
#88536000
1$
1L
b10 N
b11 N
b100 N
b101 N
b110 N
b111 N
b1000 N
b1001 N
16
15
03
02
01
10
1.
1-
0,
1+
0)
#89577600
0$
0L
#90619200
1$
1L
b10 N
b11 N
b100 N
b101 N
b110 N
b111 N
b1000 N
b1001 N
17
0*
1)
#91660800
0$
0L
#91666500
b1001 #
0I
1H
0E
05
13
12
11
1/
0-
#92702400
1$
1L
b10 N
b11 N
b100 N
b101 N
b110 N
b111 N
b1000 N
b1001 N
07
03
02
1-
1,
1*
#93744000
0$
0L
#93749900
b11001100 #
0K
1I
1E
1D
17
12
01
00
0/
0.
0-
0+
0*
0)
1(
#94785600
1$
1L
b10 N
b11 N
b100 N
b101 N
b110 N
b111 N
b1000 N
b1001 N
07
11
1/
0,
1+
1*
1)
0(
#95827200
0$
0L
#95833200
b10111100 #
1G
1F
0E
13
01
10
0/
#96868800
1$
1L
b10 N
b11 N
b100 N
b101 N
b110 N
b111 N
b1000 N
b1001 N
17
06
15
03
02
11
1-
0+
0*
#97910400
0$
0L
#97916500
b10101100 #
0G
13
01
00
#98952000
1$
1L
b10 N
b11 N
b100 N
b101 N
b110 N
b111 N
b1000 N
b1001 N
05
03
12
0-
1,
1+
#99993600
0$
0L
#99999900
b10011110 #
1J
1G
0F
16
15
02
10
1/
1.
1-
0,
#101035200
1$
1L
b10 N
b11 N
b100 N
b101 N
b110 N
b111 N
b1000 N
b1001 N
13
00
0.
0-
1,
0+
1*
0)
1(
#102076800
0$
0L
#102083200
b1111111 #
1K
1F
1E
0D
07
05
03
11
10
1.
1-
0,
#103118400
1$
1L
b10 N
b11 N
b100 N
b101 N
b110 N
b111 N
b1000 N
b1001 N
06
15
12
01
0/
0.
0*
1)
#104160000
0$
0L
#104166500
b1111001 #
0J
0I
16
05
11
00
#105201600
1$
1L
b10 N
b11 N
b100 N
b101 N
b110 N
b111 N
b1000 N
b1001 N
15
14
13
1/
1.
0-
1+
1*
0)
#106243200
0$
0L
#106249900
b11101101 #
1I
0G
1D
05
0/
0.
1,
#107284800
1$
1L
b10 N
b11 N
b100 N
b101 N
b110 N
b111 N
b1000 N
b1001 N
04
03
02
1-
0+
#108326400
0$
0L
#108333200
b11111000 #
0K
0I
1G
17
14
13
12
01
10
#109368000
1$
1L
b10 N
b11 N
b100 N
b101 N
b110 N
b111 N
b1000 N
b1001 N
07
06
15
04
02
11
0-
0,
#110409600
0$
0L
#110416500
b100110 #
1J
1I
0H
0G
0E
0D
16
14
03
1/
1.
1-
1+
0*
#111451200
1$
1L
b10 N
b11 N
b100 N
b101 N
b110 N
b111 N
b1000 N
b1001 N
17
04
13
12
01
00
0/
0-
0+
1*
#112492800
0$
0L
#112499900
b1101 #
1K
0J
1H
0F
07
06
03
1/
0.
#113534400
1$
1L
b10 N
b11 N
b100 N
b101 N
b110 N
b111 N
b1000 N
b1001 N
05
0/
1.
1,
1+
0*
1)
#114576000
0$
0L
#114583200
b10000001 #
0I
0H
1D
15
14
13
02
1/
1-
#115617600
1$
1L
b10 N
b11 N
b100 N
b101 N
b110 N
b111 N
b1000 N
b1001 N
04
03
12
11
10
0+
#116659200
0$
0L
#116666500
b11001110 #
0K
1J
1I
1H
1E
17
16
05
13
01
00
0-
0,
1+
#117700800
1$
1L
b10 N
b11 N
b100 N
b101 N
b110 N
b111 N
b1000 N
b1001 N
14
03
02
11
0/
0.
1,
0+
1*
0(
#118742400
0$
0L
#118749900
b1010101 #
1K
0J
0H
1G
0D
07
06
13
01
1/
1.
0,
#119784000
1$
1L
b10 N
b11 N
b100 N
b101 N
b110 N
b111 N
b1000 N
b1001 N
16
15
04
03
12
11
10
1-
1,
1+
0)
#120825600
0$
0L
#120833200
b111111 #
1J
1H
1F
0E
06
13
0/
#121867200
1$
1L
b10 N
b11 N
b100 N
b101 N
b110 N
b111 N
b1000 N
b1001 N
17
16
05
02
01
1/
0.
0-
0+
0*
1(
#122908800
0$
0L
#122916500
b11010 #
0K
0I
0F
07
06
15
14
12
11
1.
1-
0,
#123950400
1$
1L
b10 N
b11 N
b100 N
b101 N
b110 N
b111 N
b1000 N
b1001 N
16
04
01
0/
1*
#124992000
0$
0L
#124999900
b10110001 #
1K
0J
0H
1F
1D
17
05
00
1/
0.
1,
#126033600
1$
1L
b10 N
b11 N
b100 N
b101 N
b110 N
b111 N
b1000 N
b1001 N
10
0/
0-
1+
1)
0(
#127075200
0$
0L
#127083200
b110111 #
1J
1I
0D
06
15
11
00
1/
1.
0,
#128116800
1$
1L
b10 N
b11 N
b100 N
b101 N
b110 N
b111 N
b1000 N
b1001 N
07
05
14
03
01
10
0.
0+
0*
#129158400
0$
0L
#129166500
b1010101 #
0J
0F
1E
16
04
13
11
0/
1.
#130200000
1$
1L
b10 N
b11 N
b100 N
b101 N
b110 N
b111 N
b1000 N
b1001 N
17
06
15
14
01
00
1/
1-
1+
#131241600
0$
0L
#131249900
b111 #
1J
0G
0E
16
05
04
03
11
10
0-
#132283200
1$
1L
b10 N
b11 N
b100 N
b101 N
b110 N
b111 N
b1000 N
b1001 N
15
02
0/
1-
1*
#133324800
0$
0L
#133333200
b10111110 #
0K
1H
1G
1F
1D
07
06
12
01
1,
#134366400
1$
1L
b10 N
b11 N
b100 N
b101 N
b110 N
b111 N
b1000 N
b1001 N
17
16
05
13
11
00
0.
0+
#135408000
0$
0L
#135416500
b10110000 #
0J
0I
0H
06
14
02
10
1/
1.
0-
#136449600
1$
1L
b10 N
b11 N
b100 N
b101 N
b110 N
b111 N
b1000 N
b1001 N
07
15
12
01
0/
0.
0*
#137491200
0$
0L
#137499900
b10110100 #
1I
05
03
11
#138532800
1$
1L
b10 N
b11 N
b100 N
b101 N
b110 N
b111 N
b1000 N
b1001 N
17
15
13
02
01
1/
1.
1-
0,
1+
#139574400
0$
0L
#139583200
b10100000 #
0I
0G
05
04
03
11
0/
#140616000
1$
1L
b10 N
b11 N
b100 N
b101 N
b110 N
b111 N
b1000 N
b1001 N
14
13
12
01
00
1,
0)
1(
#141657600
0$
0L
#141666500
b1110100 #
1I
1G
1E
0D
15
04
02
11
0.
#142699200
1$
1L
b10 N
b11 N
b100 N
b101 N
b110 N
b111 N
b1000 N
b1001 N
07
16
05
1*
#143740800
0$
0L
#143749900
b1101110 #
1J
1H
0G
06
01
#144782400
1$
1L
b10 N
b11 N
b100 N
b101 N
b110 N
b111 N
b1000 N
b1001 N
12
11
10
0,
#145824000
0$
0L
#145833200
b11110011 #
1K
0I
0H
1G
1D
17
16
15
03
01
1.
0-
1,
#146865600
1$
1L
b10 N
b11 N
b100 N
b101 N
b110 N
b111 N
b1000 N
b1001 N
06
14
13
11
00
0.
1-
0+
#147907200
0$
0L
#147916500
b11111100 #
0K
0J
1I
1H
07
05
04
03
10
#148948800
1$
1L
b10 N
b11 N
b100 N
b101 N
b110 N
b111 N
b1000 N
b1001 N
15
13
02
01
0-
1+
0*
#149990400
0$
0L
#149999900
b101110 #
1J
0G
0E
0D
16
05
14
12
1/
1.
1-
0+
#151032000
1$
1L
b10 N
b11 N
b100 N
b101 N
b110 N
b111 N
b1000 N
b1001 N
17
06
15
04
02
11
0-
1+
#152073600
0$
0L
#152083200
b11110 #
1G
0F
03
12
01
00
#153115200
1$
1L
b10 N
b11 N
b100 N
b101 N
b110 N
b111 N
b1000 N
b1001 N
16
02
0.
1-
1)
#154156800
0$
0L
#154166500
b10001010 #
0I
0G
1D
05
14
12
10
0-
0,
0+
1*
#155198400
1$
1L
b10 N
b11 N
b100 N
b101 N
b110 N
b111 N
b1000 N
b1001 N
06
04
1-
1+
0*
#156240000
0$
0L
#156249900
b11001110 #
1I
1E
15
14
02
0/
0-
1,
#157281600
1$
1L
b10 N
b11 N
b100 N
b101 N
b110 N
b111 N
b1000 N
b1001 N
07
16
13
12
11
00
0,
1*
0(
#158323200
0$
0L
#158333200
b1100001 #
1K
0J
0I
0H
1F
0D
17
03
02
10
1/
1.
1,
0+
#159364800
1$
1L
b10 N
b11 N
b100 N
b101 N
b110 N
b111 N
b1000 N
b1001 N
05
12
0/
0.
1-
0*
#160406400
0$
0L
#160416500
b1010011 #
1J
1G
0F
06
04
13
02
00
#161448000
1$
1L
b10 N
b11 N
b100 N
b101 N
b110 N
b111 N
b1000 N
b1001 N
15
14
10
1/
1.
0-
0,
1+
0)
1(
#162489600
0$
0L
#162499900
b10100 #
0K
0J
1I
0E
07
05
03
12
01
00
0.
#163531200
1$
1L
b10 N
b11 N
b100 N
b101 N
b110 N
b111 N
b1000 N
b1001 N
17
16
15
10
1.
1,
0+
1*
#164572800
0$
0L
#164583200
b10100111 #
1K
1J
0G
1F
1D
07
06
05
04
02
00
0/
0,
1+
#165614400
1$
1L
b10 N
b11 N
b100 N
b101 N
b110 N
b111 N
b1000 N
b1001 N
16
15
10
1/
0+
0*
#166656000
0$
0L
#166666500
b101000 #
0K
0J
0I
1H
0D
17
06
05
13
00
0/
1-
1,
1+
1*
1)
0(
#167697600
1$
1L
b10 N
b11 N
b100 N
b101 N
b110 N
b111 N
b1000 N
b1001 N
07
16
15
14
03
12
11
10
0.
0+
0*
#168739200
0$
0L
#168749900
b1100100 #
1I
0H
1E
05
04
02
01
1/
1.
#169780800
1$
1L
b10 N
b11 N
b100 N
b101 N
b110 N
b111 N
b1000 N
b1001 N
15
13
00
0/
0.
0-
1+
#170822400
0$
0L
#170833200
b110 #
1J
0F
0E
06
14
03
1-
0,
#171864000
1$
1L
b10 N
b11 N
b100 N
b101 N
b110 N
b111 N
b1000 N
b1001 N
16
05
04
13
1/
1,
0+
1*
#172905600
0$
0L
#172916500
b10110000 #
0J
0I
1G
1F
1D
06
03
12
11
0/
0,
1+
#173947200
1$
1L
b10 N
b11 N
b100 N
b101 N
b110 N
b111 N
b1000 N
b1001 N
17
16
15
02
1.
0+
#174988800
0$
0L
#174999900
b10100100 #
1I
0G
05
10
1/
0.
#176030400
1$
1L
b10 N
b11 N
b100 N
b101 N
b110 N
b111 N
b1000 N
b1001 N
15
13
12
01
00
0/
1,
0*
#177072000
0$
0L
#177083200
b10111011 #
1K
1J
0I
1H
1G
07
06
1/
#178113600
1$
1L
b10 N
b11 N
b100 N
b101 N
b110 N
b111 N
b1000 N
b1001 N
17
05
02
11
1.
0,
1+
#179155200
0$
0L
#179166500
b10100000 #
0K
0J
0H
0G
07
14
03
12
01
0/
#180196800
1$
1L
b10 N
b11 N
b100 N
b101 N
b110 N
b111 N
b1000 N
b1001 N
17
16
15
04
13
02
11
1/
0-
0)
1(
#181238400
0$
0L
#181249900
b1101000 #
1H
1E
0D
14
03
12
10
0/
0.
#182280000
1$
1L
b10 N
b11 N
b100 N
b101 N
b110 N
b111 N
b1000 N
b1001 N
13
02
01
1/
1.
1*
#183321600
0$
0L
#183333200
b1100011 #
1K
1J
0H
07
06
05
03
12
11
00
#184363200
1$
1L
b10 N
b11 N
b100 N
b101 N
b110 N
b111 N
b1000 N
b1001 N
17
15
04
0.
1-
#185404800
0$
0L
